ptv/__init__.py
ptv/client.py
tests/__init__.py
tests/test_client.py
ptv_python_wrapper-0.1.1.dist-info/LICENSE
ptv_python_wrapper-0.1.1.dist-info/METADATA
ptv_python_wrapper-0.1.1.dist-info/WHEEL
ptv_python_wrapper-0.1.1.dist-info/top_level.txt
ptv_python_wrapper-0.1.1.dist-info/RECORD
