Metadata-Version: 2.1
Name: ptv-python-wrapper
Version: 0.1.1
Summary: An API Wrapper for Public Transport Victoria (PTV)
Home-page: https://github.com/lucky962/ptv-python-wrapper
Author: Leo Terray
Author-email: leoterray@yahoo.com.au
License: MIT
Keywords: ptv,melbourne,victoria,public transport
Platform: UNKNOWN
Classifier: Development Status :: 5 - Production/Stable
Classifier: Programming Language :: Python :: 3.6
Requires-Python: >=3.6
Requires-Dist: requests
